pycramfs/__init__.py
pycramfs/__main__.py
pycramfs/const.py
pycramfs/exception.py
pycramfs/extract.py
pycramfs/file.py
pycramfs/py.typed
pycramfs/structure.py
pycramfs/types.py
pycramfs/util.py
pycramfs-1.1.0.dist-info/LICENSE
pycramfs-1.1.0.dist-info/METADATA
pycramfs-1.1.0.dist-info/WHEEL
pycramfs-1.1.0.dist-info/entry_points.txt
pycramfs-1.1.0.dist-info/top_level.txt
pycramfs-1.1.0.dist-info/RECORD
